chocolate/__init__.py
chocolate/__main__.py
chocolate/config.py
chocolate/path.py
chocolate/project_manager.py
gochocolatego-1.4.post1.dist-info/METADATA
gochocolatego-1.4.post1.dist-info/WHEEL
gochocolatego-1.4.post1.dist-info/entry_points.txt
gochocolatego-1.4.post1.dist-info/top_level.txt
gochocolatego-1.4.post1.dist-info/RECORD
